edgelist_mapper/__init__.py
edgelist_mapper/bin/__init__.py
edgelist_mapper/bin/compute_frequency.py
edgelist_mapper/bin/generate_mapping.py
edgelist_mapper/bin/map_edgelist.py
edgelist_mapper/bin/run.py
edgelist_mapper/utils.py
edgelist_mapper-0.1.2.dist-info/WHEEL
edgelist_mapper-0.1.2.dist-info/METADATA
edgelist_mapper-0.1.2.dist-info/RECORD
