Metadata-Version: 2.1
Name: edgelist-mapper
Version: 0.1.2
Summary: Maps nodes and edges of a multi-relational graph to integer
Home-page: https://github.com/simonepri/edgelist-mapper#readme
License: MIT
Keywords: knowledge,graph,mapper,edgelist,converter
Author: Simone Primarosa
Author-email: simonepri@outlook.com
Requires-Python: >=3.6,<4.0
Classifier: License :: OSI Approved :: MIT License
Classifier: Programming Language :: Python :: 3
Classifier: Programming Language :: Python :: 3.6
Classifier: Programming Language :: Python :: 3.7
Classifier: Programming Language :: Python :: 3.8
Project-URL: Repository, https://github.com/simonepri/edgelist-mapper
